pytomoatt/__init__.py
pytomoatt/_version.py
pytomoatt/attarray.py
pytomoatt/checkerboard.py
pytomoatt/data.py
pytomoatt/distaz.py
pytomoatt/model.py
pytomoatt/para.py
pytomoatt/script.py
pytomoatt/setuplog.py
pytomoatt/src_rec.py
pytomoatt/vis.py
pytomoatt/data/crust1.0.h5
pytomoatt/io/__init__.py
pytomoatt/io/asciimodel.py
pytomoatt/io/crustmodel.py
pytomoatt/io/seispy.py
pytomoatt/template/input_params.yml
pytomoatt/template/src_rec.dat
pytomoatt/utils/__init__.py
pytomoatt/utils/common.py
pytomoatt/utils/rotate.py
pytomoatt/utils/src_rec_utils.py
pytomoatt-0.2.9.dist-info/METADATA
pytomoatt-0.2.9.dist-info/WHEEL
pytomoatt-0.2.9.dist-info/entry_points.txt
pytomoatt-0.2.9.dist-info/licenses/LICENSE
pytomoatt-0.2.9.dist-info/RECORD
