Metadata-Version: 2.4
Name: PyTomoATT
Version: 0.2.9
Summary: Your project description
Project-URL: Homepage, https://tomoatt.com/
Author: Masaru Nagaso
Author-email: Mijian Xu <gomijianxu@gmail.com>
License: GPL-3.0
License-File: LICENSE
Classifier: Programming Language :: Python
Classifier: Programming Language :: Python :: 3.9
Classifier: Programming Language :: Python :: 3.10
Classifier: Programming Language :: Python :: 3.11
Requires-Python: <4.0,>=3.9
Requires-Dist: h5py
Requires-Dist: numpy>=1.19.0
Requires-Dist: pandas>=1.4.0
Requires-Dist: pyproj
Requires-Dist: ruamel-yaml
Requires-Dist: scikit-learn
Requires-Dist: scipy
Requires-Dist: tqdm
Requires-Dist: xarray
